CHANGES.rst
CONTRIBUTORS.rst
MANIFEST.in
README.rst
setup.cfg
setup.py
docs/LICENSE.GPL
docs/LICENSE.txt
src/collective/__init__.py
src/collective.z3cform.widgets.egg-info/PKG-INFO
src/collective.z3cform.widgets.egg-info/SOURCES.txt
src/collective.z3cform.widgets.egg-info/dependency_links.txt
src/collective.z3cform.widgets.egg-info/entry_points.txt
src/collective.z3cform.widgets.egg-info/namespace_packages.txt
src/collective.z3cform.widgets.egg-info/not-zip-safe
src/collective.z3cform.widgets.egg-info/requires.txt
src/collective.z3cform.widgets.egg-info/top_level.txt
src/collective/z3cform/__init__.py
src/collective/z3cform/widgets/__init__.py
src/collective/z3cform/widgets/configure.zcml
src/collective/z3cform/widgets/enhancedtextlines.py
src/collective/z3cform/widgets/enhancedtextlines_display.pt
src/collective/z3cform/widgets/enhancedtextlines_input.pt
src/collective/z3cform/widgets/fragment.pt
src/collective/z3cform/widgets/improved_checkbox_input.pt
src/collective/z3cform/widgets/input_recurse.pt
src/collective/z3cform/widgets/interfaces.py
src/collective/z3cform/widgets/multicontent_search_widget.py
src/collective/z3cform/widgets/related_input.pt
src/collective/z3cform/widgets/related_recurse.pt
src/collective/z3cform/widgets/related_search.pt
src/collective/z3cform/widgets/related_selected.pt
src/collective/z3cform/widgets/simple_rich_text.py
src/collective/z3cform/widgets/simple_rich_text.zcml
src/collective/z3cform/widgets/simple_rich_text_display.pt
src/collective/z3cform/widgets/simple_rich_text_input.pt
src/collective/z3cform/widgets/testing.py
src/collective/z3cform/widgets/token_input_display.pt
src/collective/z3cform/widgets/token_input_input.pt
src/collective/z3cform/widgets/token_input_widget.py
src/collective/z3cform/widgets/upgrades.py
src/collective/z3cform/widgets/locales/collective.z3cform.widgets.pot
src/collective/z3cform/widgets/locales/manual.pot
src/collective/z3cform/widgets/locales/plone.pot
src/collective/z3cform/widgets/locales/es/LC_MESSAGES/collective.z3cform.widgets.po
src/collective/z3cform/widgets/locales/es/LC_MESSAGES/plone.po
src/collective/z3cform/widgets/locales/nl/LC_MESSAGES/collective.z3cform.widgets.po
src/collective/z3cform/widgets/locales/nl/LC_MESSAGES/plone.po
src/collective/z3cform/widgets/locales/pt_BR/LC_MESSAGES/collective.z3cform.widgets.po
src/collective/z3cform/widgets/locales/pt_BR/LC_MESSAGES/plone.po
