Metadata-Version: 1.0
Name: collective.z3cform.widgets
Version: 1.0b11
Summary: A widget package for Dexterity projects.
Home-page: https://github.com/collective/collective.z3cform.widgets
Author: OpenMultimedia
Author-email: contacto@openmultimedia.biz
License: GPLv2
Keywords: plone z3cform widgets dexterity
Platform: UNKNOWN
Classifier: Development Status :: 4 - Beta
Classifier: Environment :: Web Environment
Classifier: Framework :: Plone
Classifier: Framework :: Plone :: 4.2
Classifier: Framework :: Plone :: 4.3
Classifier: Intended Audience :: Developers
Classifier: License :: OSI Approved :: GNU General Public License v2 (GPLv2)
Classifier: Operating System :: OS Independent
Classifier: Programming Language :: JavaScript
Classifier: Programming Language :: Python
Classifier: Programming Language :: Python :: 2.6
Classifier: Programming Language :: Python :: 2.7
Classifier: Topic :: Office/Business :: News/Diary
Classifier: Topic :: Software Development :: Libraries :: Python Modules
Classifier: Topic :: Software Development :: User Interfaces
